{
    "horses": [
        {
            "raceId": "201907010511",
            "horseId": "2011103229",
            "umaban": "7"
        },
        {
            "raceId": "201907010509",
            "horseId": "2015102988",
            "umaban": "8"
        },
        {
            "raceId": "201907010509",
            "horseId": "2012104667",
            "umaban": "12"
        },
        {
            "raceId": "201907010509",
            "horseId": "2014100500",
            "umaban": "13"
        },
        {
            "raceId": "201907010508",
            "horseId": "2012101386",
            "umaban": "3"
        },
        {
            "raceId": "201907010508",
            "horseId": "2014104933",
            "umaban": "5"
        },
        {
            "raceId": "201907010508",
            "horseId": "2014104504",
            "umaban": "11"
        },
        {
            "raceId": "201907010507",
            "horseId": "2016104258",
            "umaban": "7"
        },
        {
            "raceId": "201907010506",
            "horseId": "2015100939",
            "umaban": "3"
        },
        {
            "raceId": "201907010506",
            "horseId": "2015104538",
            "umaban": "9"
        },
        {
            "raceId": "201907010506",
            "horseId": "2015102353",
            "umaban": "10"
        },
        {
            "raceId": "201907010505",
            "horseId": "2007100107",
            "umaban": "1"
        },
        {
            "raceId": "201907010505",
            "horseId": "2012105255",
            "umaban": "8"
        },
        {
            "raceId": "201907010505",
            "horseId": "2009100957",
            "umaban": "11"
        },
        {
            "raceId": "201907010505",
            "horseId": "2014102313",
            "umaban": "13"
        },
        {
            "raceId": "201907010504",
            "horseId": "2012104098",
            "umaban": "1"
        },
        {
            "raceId": "201907010504",
            "horseId": "2015100734",
            "umaban": "5"
        },
        {
            "raceId": "201907010504",
            "horseId": "2012105342",
            "umaban": "7"
        },
        {
            "raceId": "201907010504",
            "horseId": "2014100910",
            "umaban": "10"
        },
        {
            "raceId": "201907010504",
            "horseId": "2011100715",
            "umaban": "11"
        },
        {
            "raceId": "201907010504",
            "horseId": "2010102243",
            "umaban": "13"
        },
        {
            "raceId": "201907010504",
            "horseId": "2011101909",
            "umaban": "14"
        },
        {
            "raceId": "201907010503",
            "horseId": "2015103089",
            "umaban": "5"
        },
        {
            "raceId": "201907010503",
            "horseId": "2015100216",
            "umaban": "7"
        },
        {
            "raceId": "201907010503",
            "horseId": "2013105644",
            "umaban": "8"
        },
        {
            "raceId": "201907010503",
            "horseId": "2014101708",
            "umaban": "13"
        },
        {
            "raceId": "201907010503",
            "horseId": "2014104226",
            "umaban": "15"
        },
        {
            "raceId": "201907010502",
            "horseId": "2016100413",
            "umaban": "1"
        },
        {
            "raceId": "201907010502",
            "horseId": "2016105371",
            "umaban": "3"
        },
        {
            "raceId": "201907010502",
            "horseId": "2016104314",
            "umaban": "8"
        },
        {
            "raceId": "201907010502",
            "horseId": "2016103898",
            "umaban": "9"
        },
        {
            "raceId": "201907010502",
            "horseId": "2016102390",
            "umaban": "12"
        },
        {
            "raceId": "201907010502",
            "horseId": "2016110149",
            "umaban": "15"
        },
        {
            "raceId": "201907010501",
            "horseId": "2016101289",
            "umaban": "6"
        },
        {
            "raceId": "201907010501",
            "horseId": "2016101206",
            "umaban": "11"
        },
        {
            "raceId": "201907010412",
            "horseId": "2014105045",
            "umaban": "3"
        },
        {
            "raceId": "201907010412",
            "horseId": "2014101589",
            "umaban": "4"
        },
        {
            "raceId": "201907010412",
            "horseId": "2014105953",
            "umaban": "5"
        },
        {
            "raceId": "201907010412",
            "horseId": "2014100569",
            "umaban": "9"
        },
        {
            "raceId": "201907010412",
            "horseId": "2012105027",
            "umaban": "10"
        },
        {
            "raceId": "201907010412",
            "horseId": "2014106060",
            "umaban": "14"
        },
        {
            "raceId": "201907010411",
            "horseId": "2014105720",
            "umaban": "12"
        },
        {
            "raceId": "201907010409",
            "horseId": "2015110085",
            "umaban": "6"
        },
        {
            "raceId": "201907010409",
            "horseId": "2013104090",
            "umaban": "8"
        },
        {
            "raceId": "201907010409",
            "horseId": "2015110084",
            "umaban": "13"
        },
        {
            "raceId": "201907010409",
            "horseId": "2012101409",
            "umaban": "15"
        },
        {
            "raceId": "201907010409",
            "horseId": "2015106396",
            "umaban": "16"
        },
        {
            "raceId": "201907010408",
            "horseId": "2011103555",
            "umaban": "7"
        },
        {
            "raceId": "201907010408",
            "horseId": "2014104510",
            "umaban": "12"
        },
        {
            "raceId": "201907010408",
            "horseId": "2014103376",
            "umaban": "17"
        },
        {
            "raceId": "201907010407",
            "horseId": "2016105787",
            "umaban": "5"
        },
        {
            "raceId": "201907010407",
            "horseId": "2016101979",
            "umaban": "10"
        },
        {
            "raceId": "201907010407",
            "horseId": "2016103400",
            "umaban": "16"
        },
        {
            "raceId": "201907010406",
            "horseId": "2014103406",
            "umaban": "1"
        },
        {
            "raceId": "201907010405",
            "horseId": "2015109099",
            "umaban": "2"
        },
        {
            "raceId": "201907010405",
            "horseId": "2015106189",
            "umaban": "9"
        },
        {
            "raceId": "201907010404",
            "horseId": "2015103994",
            "umaban": "6"
        },
        {
            "raceId": "201907010404",
            "horseId": "2015106427",
            "umaban": "8"
        },
        {
            "raceId": "201907010404",
            "horseId": "2015105442",
            "umaban": "13"
        },
        {
            "raceId": "201907010403",
            "horseId": "2016104271",
            "umaban": "5"
        },
        {
            "raceId": "201907010403",
            "horseId": "2016103375",
            "umaban": "7"
        },
        {
            "raceId": "201907010403",
            "horseId": "2016106229",
            "umaban": "8"
        },
        {
            "raceId": "201907010403",
            "horseId": "2016102562",
            "umaban": "10"
        },
        {
            "raceId": "201907010403",
            "horseId": "2016105458",
            "umaban": "14"
        },
        {
            "raceId": "201907010402",
            "horseId": "2016100354",
            "umaban": "9"
        },
        {
            "raceId": "201907010402",
            "horseId": "2016100086",
            "umaban": "10"
        },
        {
            "raceId": "201907010402",
            "horseId": "2016101509",
            "umaban": "12"
        },
        {
            "raceId": "201907010402",
            "horseId": "2016101972",
            "umaban": "15"
        },
        {
            "raceId": "201907010402",
            "horseId": "2016109016",
            "umaban": "16"
        },
        {
            "raceId": "201907010312",
            "horseId": "2012104112",
            "umaban": "3"
        },
        {
            "raceId": "201907010312",
            "horseId": "2013104907",
            "umaban": "14"
        },
        {
            "raceId": "201907010311",
            "horseId": "2014105484",
            "umaban": "1"
        },
        {
            "raceId": "201907010311",
            "horseId": "2013105322",
            "umaban": "5"
        },
        {
            "raceId": "201907010311",
            "horseId": "2011103348",
            "umaban": "10"
        },
        {
            "raceId": "201907010311",
            "horseId": "2013105358",
            "umaban": "14"
        },
        {
            "raceId": "201907010310",
            "horseId": "2016100996",
            "umaban": "10"
        },
        {
            "raceId": "201907010309",
            "horseId": "2014104373",
            "umaban": "1"
        },
        {
            "raceId": "201907010308",
            "horseId": "2014102499",
            "umaban": "1"
        },
        {
            "raceId": "201907010308",
            "horseId": "2015102008",
            "umaban": "4"
        },
        {
            "raceId": "201907010308",
            "horseId": "2012103265",
            "umaban": "6"
        },
        {
            "raceId": "201907010308",
            "horseId": "2014103191",
            "umaban": "15"
        },
        {
            "raceId": "201907010308",
            "horseId": "2014101637",
            "umaban": "16"
        },
        {
            "raceId": "201907010307",
            "horseId": "2014104461",
            "umaban": "8"
        },
        {
            "raceId": "201907010306",
            "horseId": "2016100759",
            "umaban": "3"
        },
        {
            "raceId": "201907010306",
            "horseId": "2016103363",
            "umaban": "5"
        },
        {
            "raceId": "201907010306",
            "horseId": "2016106463",
            "umaban": "6"
        },
        {
            "raceId": "201907010305",
            "horseId": "2016100119",
            "umaban": "1"
        },
        {
            "raceId": "201907010305",
            "horseId": "2016101583",
            "umaban": "3"
        },
        {
            "raceId": "201907010305",
            "horseId": "2016105996",
            "umaban": "4"
        },
        {
            "raceId": "201907010305",
            "horseId": "2016100997",
            "umaban": "5"
        },
        {
            "raceId": "201907010305",
            "horseId": "2016109107",
            "umaban": "6"
        },
        {
            "raceId": "201907010305",
            "horseId": "2016103350",
            "umaban": "7"
        },
        {
            "raceId": "201907010305",
            "horseId": "2016101102",
            "umaban": "9"
        },
        {
            "raceId": "201907010305",
            "horseId": "2016103669",
            "umaban": "11"
        },
        {
            "raceId": "201907010305",
            "horseId": "2016100117",
            "umaban": "13"
        },
        {
            "raceId": "201907010304",
            "horseId": "2014105065",
            "umaban": "8"
        },
        {
            "raceId": "201907010304",
            "horseId": "2013104051",
            "umaban": "10"
        },
        {
            "raceId": "201907010303",
            "horseId": "2016106350",
            "umaban": "9"
        },
        {
            "raceId": "201907010302",
            "horseId": "2016103480",
            "umaban": "3"
        },
        {
            "raceId": "201907010302",
            "horseId": "2016103705",
            "umaban": "8"
        }
    ]
}