{
    "horses": [
        {
            "raceId": "202205030202",
            "horseId": "2019101581",
            "umaban": "7"
        },
        {
            "raceId": "202205030201",
            "horseId": "2019101004",
            "umaban": "3"
        },
        {
            "raceId": "202205030112",
            "horseId": "2016101561",
            "umaban": "3"
        },
        {
            "raceId": "202205030111",
            "horseId": "2014102862",
            "umaban": "1"
        },
        {
            "raceId": "202205030111",
            "horseId": "2017106589",
            "umaban": "4"
        },
        {
            "raceId": "202205030110",
            "horseId": "2017103666",
            "umaban": "6"
        },
        {
            "raceId": "202205030108",
            "horseId": "2018101716",
            "umaban": "15"
        },
        {
            "raceId": "202205030107",
            "horseId": "2017100424",
            "umaban": "7"
        },
        {
            "raceId": "202205030105",
            "horseId": "2020102513",
            "umaban": "8"
        },
        {
            "raceId": "202205030104",
            "horseId": "2019105268",
            "umaban": "1"
        },
        {
            "raceId": "202205030104",
            "horseId": "2019101745",
            "umaban": "10"
        },
        {
            "raceId": "202205030104",
            "horseId": "2019101039",
            "umaban": "15"
        },
        {
            "raceId": "202205030103",
            "horseId": "2019105408",
            "umaban": "4"
        },
        {
            "raceId": "202205030103",
            "horseId": "2019105608",
            "umaban": "6"
        },
        {
            "raceId": "202205030103",
            "horseId": "2019100373",
            "umaban": "8"
        },
        {
            "raceId": "202205030103",
            "horseId": "2019105254",
            "umaban": "10"
        },
        {
            "raceId": "202205030102",
            "horseId": "2019103348",
            "umaban": "1"
        },
        {
            "raceId": "202205030102",
            "horseId": "2019102004",
            "umaban": "9"
        },
        {
            "raceId": "202205021206",
            "horseId": "2016104818",
            "umaban": "9"
        },
        {
            "raceId": "202205021204",
            "horseId": "2019104659",
            "umaban": "2"
        },
        {
            "raceId": "202205021204",
            "horseId": "2019110029",
            "umaban": "6"
        },
        {
            "raceId": "202205021204",
            "horseId": "2019106800",
            "umaban": "14"
        },
        {
            "raceId": "202205021204",
            "horseId": "2019101420",
            "umaban": "16"
        },
        {
            "raceId": "202205021202",
            "horseId": "2019101595",
            "umaban": "1"
        },
        {
            "raceId": "202205021202",
            "horseId": "2019105026",
            "umaban": "5"
        },
        {
            "raceId": "202205021201",
            "horseId": "2019105086",
            "umaban": "9"
        },
        {
            "raceId": "202205021112",
            "horseId": "2017103888",
            "umaban": "4"
        },
        {
            "raceId": "202205021108",
            "horseId": "2018100715",
            "umaban": "10"
        },
        {
            "raceId": "202205021105",
            "horseId": "2019104863",
            "umaban": "4"
        },
        {
            "raceId": "202205021105",
            "horseId": "2019105231",
            "umaban": "13"
        },
        {
            "raceId": "202205021104",
            "horseId": "2019110023",
            "umaban": "1"
        },
        {
            "raceId": "202205021104",
            "horseId": "2019106888",
            "umaban": "8"
        },
        {
            "raceId": "202205021104",
            "horseId": "2019106695",
            "umaban": "9"
        },
        {
            "raceId": "202205021104",
            "horseId": "2019102225",
            "umaban": "14"
        },
        {
            "raceId": "202205021103",
            "horseId": "2019100591",
            "umaban": "4"
        },
        {
            "raceId": "202205021103",
            "horseId": "2019101559",
            "umaban": "9"
        },
        {
            "raceId": "202205021101",
            "horseId": "2019104815",
            "umaban": "6"
        },
        {
            "raceId": "202205021101",
            "horseId": "2019106727",
            "umaban": "8"
        },
        {
            "raceId": "202205021101",
            "horseId": "2019106735",
            "umaban": "15"
        },
        {
            "raceId": "202205021004",
            "horseId": "2019101490",
            "umaban": "10"
        },
        {
            "raceId": "202205021003",
            "horseId": "2019100147",
            "umaban": "1"
        },
        {
            "raceId": "202205021003",
            "horseId": "2019105310",
            "umaban": "3"
        },
        {
            "raceId": "202205021002",
            "horseId": "2019105234",
            "umaban": "3"
        },
        {
            "raceId": "202205021001",
            "horseId": "2019100839",
            "umaban": "4"
        },
        {
            "raceId": "202205021001",
            "horseId": "2019101892",
            "umaban": "8"
        },
        {
            "raceId": "202205021001",
            "horseId": "2019103432",
            "umaban": "9"
        },
        {
            "raceId": "202205021001",
            "horseId": "2019101323",
            "umaban": "14"
        },
        {
            "raceId": "202205021001",
            "horseId": "2019103990",
            "umaban": "15"
        },
        {
            "raceId": "202205020912",
            "horseId": "2018102023",
            "umaban": "5"
        },
        {
            "raceId": "202205020908",
            "horseId": "2016101604",
            "umaban": "2"
        }
    ]
}