{
    "horses": [
        {
            "raceId": "202205030805",
            "horseId": "2020102350",
            "umaban": "12"
        },
        {
            "raceId": "202205030804",
            "horseId": "2019106200",
            "umaban": "2"
        },
        {
            "raceId": "202205030804",
            "horseId": "2019105724",
            "umaban": "11"
        },
        {
            "raceId": "202205030803",
            "horseId": "2019106021",
            "umaban": "1"
        },
        {
            "raceId": "202205030803",
            "horseId": "2019105405",
            "umaban": "6"
        },
        {
            "raceId": "202205030803",
            "horseId": "2019105360",
            "umaban": "7"
        },
        {
            "raceId": "202205030802",
            "horseId": "2019105960",
            "umaban": "2"
        },
        {
            "raceId": "202205030802",
            "horseId": "2019109091",
            "umaban": "5"
        },
        {
            "raceId": "202205030802",
            "horseId": "2019102318",
            "umaban": "6"
        },
        {
            "raceId": "202205030802",
            "horseId": "2019101457",
            "umaban": "14"
        },
        {
            "raceId": "202205030801",
            "horseId": "2019103640",
            "umaban": "1"
        },
        {
            "raceId": "202205030801",
            "horseId": "2019105033",
            "umaban": "7"
        },
        {
            "raceId": "202205030712",
            "horseId": "2019101915",
            "umaban": "2"
        },
        {
            "raceId": "202205030712",
            "horseId": "2019100123",
            "umaban": "9"
        },
        {
            "raceId": "202205030709",
            "horseId": "2017106334",
            "umaban": "8"
        },
        {
            "raceId": "202205030709",
            "horseId": "2016106527",
            "umaban": "10"
        },
        {
            "raceId": "202205030706",
            "horseId": "2019104827",
            "umaban": "3"
        },
        {
            "raceId": "202205030706",
            "horseId": "2019106317",
            "umaban": "7"
        },
        {
            "raceId": "202205030706",
            "horseId": "2019100039",
            "umaban": "9"
        },
        {
            "raceId": "202205030706",
            "horseId": "2019104581",
            "umaban": "10"
        },
        {
            "raceId": "202205030706",
            "horseId": "2019104662",
            "umaban": "12"
        },
        {
            "raceId": "202205030706",
            "horseId": "2019100609",
            "umaban": "15"
        },
        {
            "raceId": "202205030705",
            "horseId": "2020103017",
            "umaban": "1"
        },
        {
            "raceId": "202205030705",
            "horseId": "2020106414",
            "umaban": "10"
        },
        {
            "raceId": "202205030704",
            "horseId": "2019101009",
            "umaban": "2"
        },
        {
            "raceId": "202205030703",
            "horseId": "2019104241",
            "umaban": "4"
        },
        {
            "raceId": "202205030703",
            "horseId": "2019109040",
            "umaban": "9"
        },
        {
            "raceId": "202205030703",
            "horseId": "2019106749",
            "umaban": "13"
        },
        {
            "raceId": "202205030703",
            "horseId": "2019105998",
            "umaban": "15"
        },
        {
            "raceId": "202205030703",
            "horseId": "2019100102",
            "umaban": "16"
        },
        {
            "raceId": "202205030702",
            "horseId": "2019101843",
            "umaban": "4"
        },
        {
            "raceId": "202205030702",
            "horseId": "2019102699",
            "umaban": "6"
        },
        {
            "raceId": "202205030702",
            "horseId": "2019104003",
            "umaban": "8"
        },
        {
            "raceId": "202205030702",
            "horseId": "2019102132",
            "umaban": "10"
        },
        {
            "raceId": "202205030702",
            "horseId": "2019103153",
            "umaban": "13"
        },
        {
            "raceId": "202205030701",
            "horseId": "2020104216",
            "umaban": "9"
        },
        {
            "raceId": "202205030612",
            "horseId": "2018104180",
            "umaban": "6"
        },
        {
            "raceId": "202205030612",
            "horseId": "2018105374",
            "umaban": "8"
        },
        {
            "raceId": "202205030612",
            "horseId": "2019104324",
            "umaban": "11"
        },
        {
            "raceId": "202205030612",
            "horseId": "2018103448",
            "umaban": "14"
        },
        {
            "raceId": "202205030612",
            "horseId": "2016102406",
            "umaban": "16"
        },
        {
            "raceId": "202205030608",
            "horseId": "2017102918",
            "umaban": "2"
        },
        {
            "raceId": "202205030607",
            "horseId": "2018101457",
            "umaban": "9"
        },
        {
            "raceId": "202205030606",
            "horseId": "2020104149",
            "umaban": "13"
        },
        {
            "raceId": "202205030605",
            "horseId": "2020102283",
            "umaban": "10"
        },
        {
            "raceId": "202205030604",
            "horseId": "2019103492",
            "umaban": "13"
        },
        {
            "raceId": "202205030603",
            "horseId": "2019105422",
            "umaban": "3"
        },
        {
            "raceId": "202205030603",
            "horseId": "2019103170",
            "umaban": "4"
        },
        {
            "raceId": "202205030603",
            "horseId": "2019104110",
            "umaban": "5"
        },
        {
            "raceId": "202205030603",
            "horseId": "2019106144",
            "umaban": "11"
        },
        {
            "raceId": "202205030602",
            "horseId": "2019104974",
            "umaban": "15"
        },
        {
            "raceId": "202205030602",
            "horseId": "2019101870",
            "umaban": "16"
        },
        {
            "raceId": "202205030512",
            "horseId": "2017110163",
            "umaban": "5"
        },
        {
            "raceId": "202205030507",
            "horseId": "2019106828",
            "umaban": "4"
        },
        {
            "raceId": "202205030507",
            "horseId": "2019102415",
            "umaban": "10"
        },
        {
            "raceId": "202205030506",
            "horseId": "2019105723",
            "umaban": "7"
        },
        {
            "raceId": "202205030506",
            "horseId": "2019103514",
            "umaban": "13"
        },
        {
            "raceId": "202205030506",
            "horseId": "2019109016",
            "umaban": "14"
        },
        {
            "raceId": "202205030505",
            "horseId": "2020102379",
            "umaban": "5"
        },
        {
            "raceId": "202205030505",
            "horseId": "2020104265",
            "umaban": "12"
        },
        {
            "raceId": "202205030504",
            "horseId": "2019104035",
            "umaban": "2"
        },
        {
            "raceId": "202205030504",
            "horseId": "2019103455",
            "umaban": "4"
        },
        {
            "raceId": "202205030504",
            "horseId": "2019102546",
            "umaban": "7"
        },
        {
            "raceId": "202205030504",
            "horseId": "2019100746",
            "umaban": "8"
        },
        {
            "raceId": "202205030504",
            "horseId": "2019100747",
            "umaban": "14"
        },
        {
            "raceId": "202205030502",
            "horseId": "2019100999",
            "umaban": "14"
        },
        {
            "raceId": "202205030411",
            "horseId": "2016103815",
            "umaban": "7"
        },
        {
            "raceId": "202205030409",
            "horseId": "2016100757",
            "umaban": "5"
        },
        {
            "raceId": "202205030407",
            "horseId": "2015106095",
            "umaban": "12"
        },
        {
            "raceId": "202205030406",
            "horseId": "2019103932",
            "umaban": "2"
        },
        {
            "raceId": "202205030406",
            "horseId": "2019101117",
            "umaban": "3"
        },
        {
            "raceId": "202205030405",
            "horseId": "2020102518",
            "umaban": "10"
        },
        {
            "raceId": "202205030404",
            "horseId": "2019104647",
            "umaban": "6"
        },
        {
            "raceId": "202205030404",
            "horseId": "2019102071",
            "umaban": "9"
        },
        {
            "raceId": "202205030404",
            "horseId": "2019100827",
            "umaban": "14"
        },
        {
            "raceId": "202205030404",
            "horseId": "2019100143",
            "umaban": "16"
        },
        {
            "raceId": "202205030403",
            "horseId": "2019104377",
            "umaban": "1"
        },
        {
            "raceId": "202205030403",
            "horseId": "2019101787",
            "umaban": "3"
        },
        {
            "raceId": "202205030403",
            "horseId": "2019102007",
            "umaban": "11"
        },
        {
            "raceId": "202205030401",
            "horseId": "2019105266",
            "umaban": "2"
        },
        {
            "raceId": "202205030401",
            "horseId": "2019103625",
            "umaban": "3"
        },
        {
            "raceId": "202205030401",
            "horseId": "2019104136",
            "umaban": "5"
        },
        {
            "raceId": "202205030305",
            "horseId": "2020102474",
            "umaban": "10"
        },
        {
            "raceId": "202205030304",
            "horseId": "2019104226",
            "umaban": "3"
        },
        {
            "raceId": "202205030304",
            "horseId": "2019110069",
            "umaban": "6"
        },
        {
            "raceId": "202205030304",
            "horseId": "2019106187",
            "umaban": "12"
        },
        {
            "raceId": "202205030304",
            "horseId": "2019110126",
            "umaban": "18"
        },
        {
            "raceId": "202205030303",
            "horseId": "2019103957",
            "umaban": "14"
        },
        {
            "raceId": "202205030302",
            "horseId": "2019103560",
            "umaban": "11"
        },
        {
            "raceId": "202205030211",
            "horseId": "2016105067",
            "umaban": "2"
        },
        {
            "raceId": "202205030211",
            "horseId": "2018105181",
            "umaban": "7"
        },
        {
            "raceId": "202205030208",
            "horseId": "2016102884",
            "umaban": "11"
        },
        {
            "raceId": "202205030207",
            "horseId": "2019101329",
            "umaban": "10"
        },
        {
            "raceId": "202205030206",
            "horseId": "2020102752",
            "umaban": "12"
        },
        {
            "raceId": "202205030206",
            "horseId": "2020100615",
            "umaban": "14"
        },
        {
            "raceId": "202205030205",
            "horseId": "2020101349",
            "umaban": "1"
        },
        {
            "raceId": "202205030204",
            "horseId": "2019105639",
            "umaban": "5"
        },
        {
            "raceId": "202205030203",
            "horseId": "2019105712",
            "umaban": "1"
        },
        {
            "raceId": "202205030203",
            "horseId": "2019105390",
            "umaban": "8"
        },
        {
            "raceId": "202205030203",
            "horseId": "2019109020",
            "umaban": "15"
        }
    ]
}