{
    "horses": [
        {
            "raceId": "202009020302",
            "horseId": "2017101732",
            "umaban": "14"
        },
        {
            "raceId": "202009020301",
            "horseId": "2017104934",
            "umaban": "2"
        },
        {
            "raceId": "202009020301",
            "horseId": "2017101021",
            "umaban": "3"
        },
        {
            "raceId": "202009020301",
            "horseId": "2017100966",
            "umaban": "8"
        },
        {
            "raceId": "202009020301",
            "horseId": "2017106393",
            "umaban": "10"
        },
        {
            "raceId": "202009020301",
            "horseId": "2017105593",
            "umaban": "11"
        },
        {
            "raceId": "202009020301",
            "horseId": "2017103700",
            "umaban": "14"
        },
        {
            "raceId": "202009020212",
            "horseId": "2014102735",
            "umaban": "12"
        },
        {
            "raceId": "202009020212",
            "horseId": "2016101105",
            "umaban": "14"
        },
        {
            "raceId": "202009020211",
            "horseId": "2015110035",
            "umaban": "4"
        },
        {
            "raceId": "202009020211",
            "horseId": "2015104188",
            "umaban": "8"
        },
        {
            "raceId": "202009020211",
            "horseId": "2015101636",
            "umaban": "11"
        },
        {
            "raceId": "202009020211",
            "horseId": "2014103009",
            "umaban": "13"
        },
        {
            "raceId": "202009020210",
            "horseId": "2014105543",
            "umaban": "2"
        },
        {
            "raceId": "202009020208",
            "horseId": "2016100235",
            "umaban": "1"
        },
        {
            "raceId": "202009020207",
            "horseId": "2017102412",
            "umaban": "1"
        },
        {
            "raceId": "202009020207",
            "horseId": "2017100765",
            "umaban": "4"
        },
        {
            "raceId": "202009020206",
            "horseId": "2017110039",
            "umaban": "1"
        },
        {
            "raceId": "202009020206",
            "horseId": "2017101430",
            "umaban": "4"
        },
        {
            "raceId": "202009020206",
            "horseId": "2017102283",
            "umaban": "13"
        },
        {
            "raceId": "202009020206",
            "horseId": "2017103568",
            "umaban": "16"
        },
        {
            "raceId": "202009020205",
            "horseId": "2017104656",
            "umaban": "2"
        },
        {
            "raceId": "202009020205",
            "horseId": "2017103133",
            "umaban": "8"
        },
        {
            "raceId": "202009020205",
            "horseId": "2017103159",
            "umaban": "14"
        },
        {
            "raceId": "202009020205",
            "horseId": "2017103349",
            "umaban": "15"
        },
        {
            "raceId": "202009020204",
            "horseId": "2012104268",
            "umaban": "1"
        },
        {
            "raceId": "202009020204",
            "horseId": "2012103930",
            "umaban": "2"
        },
        {
            "raceId": "202009020204",
            "horseId": "2016100954",
            "umaban": "3"
        },
        {
            "raceId": "202009020204",
            "horseId": "2014105365",
            "umaban": "4"
        },
        {
            "raceId": "202009020204",
            "horseId": "2014104375",
            "umaban": "6"
        },
        {
            "raceId": "202009020204",
            "horseId": "2016102217",
            "umaban": "8"
        },
        {
            "raceId": "202009020204",
            "horseId": "2013101249",
            "umaban": "10"
        },
        {
            "raceId": "202009020203",
            "horseId": "2017100039",
            "umaban": "1"
        },
        {
            "raceId": "202009020203",
            "horseId": "2017106412",
            "umaban": "2"
        },
        {
            "raceId": "202009020203",
            "horseId": "2017106698",
            "umaban": "8"
        },
        {
            "raceId": "202009020203",
            "horseId": "2017104654",
            "umaban": "10"
        },
        {
            "raceId": "202009020203",
            "horseId": "2017104715",
            "umaban": "13"
        },
        {
            "raceId": "202009020203",
            "horseId": "2017101825",
            "umaban": "14"
        },
        {
            "raceId": "202009020202",
            "horseId": "2017102219",
            "umaban": "2"
        },
        {
            "raceId": "202009020202",
            "horseId": "2017102748",
            "umaban": "3"
        },
        {
            "raceId": "202009020202",
            "horseId": "2017106213",
            "umaban": "5"
        },
        {
            "raceId": "202009020202",
            "horseId": "2017104289",
            "umaban": "6"
        },
        {
            "raceId": "202009020202",
            "horseId": "2017101793",
            "umaban": "15"
        },
        {
            "raceId": "202009020201",
            "horseId": "2017104148",
            "umaban": "4"
        },
        {
            "raceId": "202009020201",
            "horseId": "2017106100",
            "umaban": "11"
        },
        {
            "raceId": "202009020112",
            "horseId": "2016104224",
            "umaban": "1"
        },
        {
            "raceId": "202009020112",
            "horseId": "2016102642",
            "umaban": "6"
        },
        {
            "raceId": "202009020111",
            "horseId": "2017103548",
            "umaban": "9"
        },
        {
            "raceId": "202009020110",
            "horseId": "2015100523",
            "umaban": "2"
        },
        {
            "raceId": "202009020110",
            "horseId": "2011104859",
            "umaban": "8"
        },
        {
            "raceId": "202009020108",
            "horseId": "2016103416",
            "umaban": "6"
        },
        {
            "raceId": "202009020105",
            "horseId": "2017105654",
            "umaban": "2"
        },
        {
            "raceId": "202009020105",
            "horseId": "2017105625",
            "umaban": "4"
        },
        {
            "raceId": "202009020105",
            "horseId": "2017105166",
            "umaban": "6"
        },
        {
            "raceId": "202009020105",
            "horseId": "2017104750",
            "umaban": "7"
        },
        {
            "raceId": "202009020104",
            "horseId": "2017103092",
            "umaban": "2"
        },
        {
            "raceId": "202009020104",
            "horseId": "2017100618",
            "umaban": "5"
        },
        {
            "raceId": "202009020104",
            "horseId": "2017105076",
            "umaban": "8"
        },
        {
            "raceId": "202009020104",
            "horseId": "2017106403",
            "umaban": "9"
        },
        {
            "raceId": "202009020104",
            "horseId": "2017104772",
            "umaban": "10"
        },
        {
            "raceId": "202009020104",
            "horseId": "2017103675",
            "umaban": "15"
        },
        {
            "raceId": "202009020103",
            "horseId": "2017101001",
            "umaban": "1"
        },
        {
            "raceId": "202009020103",
            "horseId": "2017106664",
            "umaban": "7"
        },
        {
            "raceId": "202009020103",
            "horseId": "2017102237",
            "umaban": "12"
        },
        {
            "raceId": "202009020102",
            "horseId": "2017102381",
            "umaban": "2"
        },
        {
            "raceId": "202009020102",
            "horseId": "2017102605",
            "umaban": "14"
        },
        {
            "raceId": "202009020101",
            "horseId": "2017101729",
            "umaban": "4"
        },
        {
            "raceId": "202009020101",
            "horseId": "2017102067",
            "umaban": "8"
        },
        {
            "raceId": "202009010912",
            "horseId": "2016105147",
            "umaban": "6"
        },
        {
            "raceId": "202009010912",
            "horseId": "2016101941",
            "umaban": "8"
        },
        {
            "raceId": "202009010912",
            "horseId": "2014106210",
            "umaban": "10"
        },
        {
            "raceId": "202009010912",
            "horseId": "2015104475",
            "umaban": "13"
        },
        {
            "raceId": "202009010912",
            "horseId": "2015104333",
            "umaban": "14"
        },
        {
            "raceId": "202009010911",
            "horseId": "2015104897",
            "umaban": "1"
        },
        {
            "raceId": "202009010911",
            "horseId": "2013105975",
            "umaban": "8"
        },
        {
            "raceId": "202009010910",
            "horseId": "2015106351",
            "umaban": "8"
        },
        {
            "raceId": "202009010910",
            "horseId": "2015104376",
            "umaban": "10"
        },
        {
            "raceId": "202009010910",
            "horseId": "2014101023",
            "umaban": "12"
        },
        {
            "raceId": "202009010910",
            "horseId": "2015101229",
            "umaban": "15"
        },
        {
            "raceId": "202009010908",
            "horseId": "2015101375",
            "umaban": "3"
        },
        {
            "raceId": "202009010908",
            "horseId": "2015106036",
            "umaban": "9"
        },
        {
            "raceId": "202009010908",
            "horseId": "2016100136",
            "umaban": "10"
        },
        {
            "raceId": "202009010907",
            "horseId": "2013102945",
            "umaban": "7"
        },
        {
            "raceId": "202009010905",
            "horseId": "2017104169",
            "umaban": "1"
        },
        {
            "raceId": "202009010905",
            "horseId": "2017101992",
            "umaban": "12"
        },
        {
            "raceId": "202009010905",
            "horseId": "2017105980",
            "umaban": "13"
        },
        {
            "raceId": "202009010904",
            "horseId": "2014103687",
            "umaban": "3"
        },
        {
            "raceId": "202009010904",
            "horseId": "2014103710",
            "umaban": "5"
        },
        {
            "raceId": "202009010904",
            "horseId": "2016101385",
            "umaban": "6"
        },
        {
            "raceId": "202009010904",
            "horseId": "2016101721",
            "umaban": "10"
        },
        {
            "raceId": "202009010904",
            "horseId": "2014101666",
            "umaban": "14"
        },
        {
            "raceId": "202009010902",
            "horseId": "2017106345",
            "umaban": "5"
        },
        {
            "raceId": "202009010902",
            "horseId": "2017101289",
            "umaban": "7"
        },
        {
            "raceId": "202009010902",
            "horseId": "2017101845",
            "umaban": "8"
        },
        {
            "raceId": "202009010901",
            "horseId": "2017104338",
            "umaban": "5"
        },
        {
            "raceId": "202009010901",
            "horseId": "2017103794",
            "umaban": "7"
        },
        {
            "raceId": "202009010901",
            "horseId": "2017104752",
            "umaban": "11"
        },
        {
            "raceId": "202009010901",
            "horseId": "2017104780",
            "umaban": "12"
        },
        {
            "raceId": "202009010812",
            "horseId": "2015102370",
            "umaban": "1"
        },
        {
            "raceId": "202009010812",
            "horseId": "2015100153",
            "umaban": "2"
        }
    ]
}