{
    "horses": [
        {
            "raceId": "202307011205",
            "horseId": "2020107209",
            "umaban": "6"
        },
        {
            "raceId": "202307011205",
            "horseId": "2020105369",
            "umaban": "10"
        },
        {
            "raceId": "202307011203",
            "horseId": "2020105725",
            "umaban": "2"
        },
        {
            "raceId": "202307011203",
            "horseId": "2020106968",
            "umaban": "6"
        },
        {
            "raceId": "202307011203",
            "horseId": "2020106665",
            "umaban": "12"
        },
        {
            "raceId": "202307011203",
            "horseId": "2020105371",
            "umaban": "13"
        },
        {
            "raceId": "202307011203",
            "horseId": "2020106620",
            "umaban": "16"
        },
        {
            "raceId": "202307011202",
            "horseId": "2020105463",
            "umaban": "4"
        },
        {
            "raceId": "202307011202",
            "horseId": "2020101215",
            "umaban": "5"
        },
        {
            "raceId": "202307011202",
            "horseId": "2020101442",
            "umaban": "9"
        },
        {
            "raceId": "202307011202",
            "horseId": "2020105019",
            "umaban": "14"
        },
        {
            "raceId": "202307011112",
            "horseId": "2019106370",
            "umaban": "4"
        },
        {
            "raceId": "202307011111",
            "horseId": "2017102031",
            "umaban": "1"
        },
        {
            "raceId": "202307011111",
            "horseId": "2017103803",
            "umaban": "4"
        },
        {
            "raceId": "202307011111",
            "horseId": "2016105047",
            "umaban": "9"
        },
        {
            "raceId": "202307011111",
            "horseId": "2016104231",
            "umaban": "12"
        },
        {
            "raceId": "202307011111",
            "horseId": "2018104876",
            "umaban": "13"
        },
        {
            "raceId": "202307011111",
            "horseId": "2017105416",
            "umaban": "15"
        },
        {
            "raceId": "202307011108",
            "horseId": "2015106353",
            "umaban": "2"
        },
        {
            "raceId": "202307011108",
            "horseId": "2018105007",
            "umaban": "4"
        },
        {
            "raceId": "202307011108",
            "horseId": "2017101791",
            "umaban": "8"
        },
        {
            "raceId": "202307011108",
            "horseId": "2018102600",
            "umaban": "12"
        },
        {
            "raceId": "202307011107",
            "horseId": "2016100305",
            "umaban": "2"
        },
        {
            "raceId": "202307011106",
            "horseId": "2016101391",
            "umaban": "14"
        },
        {
            "raceId": "202307011105",
            "horseId": "2020104952",
            "umaban": "4"
        },
        {
            "raceId": "202307011105",
            "horseId": "2020101469",
            "umaban": "9"
        },
        {
            "raceId": "202307011103",
            "horseId": "2020103097",
            "umaban": "7"
        },
        {
            "raceId": "202307011103",
            "horseId": "2020106542",
            "umaban": "12"
        },
        {
            "raceId": "202307011102",
            "horseId": "2020100841",
            "umaban": "3"
        },
        {
            "raceId": "202307011102",
            "horseId": "2020102060",
            "umaban": "16"
        },
        {
            "raceId": "202307011101",
            "horseId": "2020107089",
            "umaban": "5"
        },
        {
            "raceId": "202307011101",
            "horseId": "2020100642",
            "umaban": "9"
        },
        {
            "raceId": "202307011101",
            "horseId": "2020101239",
            "umaban": "15"
        },
        {
            "raceId": "202307011012",
            "horseId": "2019102537",
            "umaban": "1"
        },
        {
            "raceId": "202307011011",
            "horseId": "2017105541",
            "umaban": "1"
        },
        {
            "raceId": "202307011011",
            "horseId": "2016103143",
            "umaban": "4"
        },
        {
            "raceId": "202307011011",
            "horseId": "2018104029",
            "umaban": "6"
        },
        {
            "raceId": "202307011011",
            "horseId": "2016110152",
            "umaban": "7"
        },
        {
            "raceId": "202307011011",
            "horseId": "2016103415",
            "umaban": "10"
        },
        {
            "raceId": "202307011010",
            "horseId": "2017103117",
            "umaban": "2"
        },
        {
            "raceId": "202307011010",
            "horseId": "2018105583",
            "umaban": "6"
        },
        {
            "raceId": "202307011010",
            "horseId": "2017102802",
            "umaban": "14"
        },
        {
            "raceId": "202307011009",
            "horseId": "2017104989",
            "umaban": "4"
        },
        {
            "raceId": "202307011009",
            "horseId": "2017104988",
            "umaban": "6"
        },
        {
            "raceId": "202307011009",
            "horseId": "2017110029",
            "umaban": "7"
        },
        {
            "raceId": "202307011008",
            "horseId": "2018106193",
            "umaban": "11"
        },
        {
            "raceId": "202307011005",
            "horseId": "2020103596",
            "umaban": "5"
        },
        {
            "raceId": "202307011004",
            "horseId": "2020102352",
            "umaban": "1"
        },
        {
            "raceId": "202307011004",
            "horseId": "2020101832",
            "umaban": "5"
        },
        {
            "raceId": "202307011003",
            "horseId": "2020100922",
            "umaban": "4"
        },
        {
            "raceId": "202307011003",
            "horseId": "2020106046",
            "umaban": "12"
        },
        {
            "raceId": "202307011003",
            "horseId": "2020103761",
            "umaban": "14"
        },
        {
            "raceId": "202307011001",
            "horseId": "2020104387",
            "umaban": "4"
        },
        {
            "raceId": "202307010911",
            "horseId": "2017103482",
            "umaban": "8"
        },
        {
            "raceId": "202307010911",
            "horseId": "2018106502",
            "umaban": "16"
        },
        {
            "raceId": "202307010910",
            "horseId": "2017104670",
            "umaban": "4"
        },
        {
            "raceId": "202307010908",
            "horseId": "2018103303",
            "umaban": "3"
        },
        {
            "raceId": "202307010908",
            "horseId": "2017100081",
            "umaban": "4"
        },
        {
            "raceId": "202307010908",
            "horseId": "2017109098",
            "umaban": "6"
        },
        {
            "raceId": "202307010908",
            "horseId": "2018101141",
            "umaban": "8"
        },
        {
            "raceId": "202307010906",
            "horseId": "2020100846",
            "umaban": "12"
        },
        {
            "raceId": "202307010904",
            "horseId": "2020105589",
            "umaban": "7"
        },
        {
            "raceId": "202307010903",
            "horseId": "2020109074",
            "umaban": "4"
        },
        {
            "raceId": "202307010903",
            "horseId": "2020101264",
            "umaban": "5"
        },
        {
            "raceId": "202307010903",
            "horseId": "2020106571",
            "umaban": "8"
        },
        {
            "raceId": "202307010903",
            "horseId": "2020105901",
            "umaban": "15"
        },
        {
            "raceId": "202307010901",
            "horseId": "2020104109",
            "umaban": "4"
        },
        {
            "raceId": "202307010811",
            "horseId": "2016101455",
            "umaban": "2"
        },
        {
            "raceId": "202307010811",
            "horseId": "2016105713",
            "umaban": "13"
        },
        {
            "raceId": "202307010810",
            "horseId": "2017104688",
            "umaban": "10"
        },
        {
            "raceId": "202307010808",
            "horseId": "2017100825",
            "umaban": "13"
        },
        {
            "raceId": "202307010807",
            "horseId": "2019105495",
            "umaban": "9"
        },
        {
            "raceId": "202307010806",
            "horseId": "2020104333",
            "umaban": "8"
        },
        {
            "raceId": "202307010806",
            "horseId": "2020105202",
            "umaban": "9"
        },
        {
            "raceId": "202307010805",
            "horseId": "2020101300",
            "umaban": "4"
        },
        {
            "raceId": "202307010805",
            "horseId": "2020100670",
            "umaban": "6"
        },
        {
            "raceId": "202307010805",
            "horseId": "2020101684",
            "umaban": "8"
        },
        {
            "raceId": "202307010803",
            "horseId": "2020100750",
            "umaban": "1"
        },
        {
            "raceId": "202307010803",
            "horseId": "2020104819",
            "umaban": "3"
        },
        {
            "raceId": "202307010803",
            "horseId": "2020104646",
            "umaban": "5"
        },
        {
            "raceId": "202307010803",
            "horseId": "2020100531",
            "umaban": "6"
        },
        {
            "raceId": "202307010803",
            "horseId": "2020105846",
            "umaban": "10"
        },
        {
            "raceId": "202307010802",
            "horseId": "2020105532",
            "umaban": "4"
        },
        {
            "raceId": "202307010802",
            "horseId": "2020104283",
            "umaban": "7"
        },
        {
            "raceId": "202307010802",
            "horseId": "2020100667",
            "umaban": "14"
        },
        {
            "raceId": "202307010801",
            "horseId": "2020100340",
            "umaban": "5"
        },
        {
            "raceId": "202307010801",
            "horseId": "2020101392",
            "umaban": "7"
        },
        {
            "raceId": "202307010712",
            "horseId": "2018105123",
            "umaban": "5"
        },
        {
            "raceId": "202307010712",
            "horseId": "2019105321",
            "umaban": "7"
        },
        {
            "raceId": "202307010711",
            "horseId": "2017105354",
            "umaban": "2"
        },
        {
            "raceId": "202307010709",
            "horseId": "2018102290",
            "umaban": "5"
        },
        {
            "raceId": "202307010709",
            "horseId": "2018104966",
            "umaban": "10"
        },
        {
            "raceId": "202307010709",
            "horseId": "2017105308",
            "umaban": "11"
        },
        {
            "raceId": "202307010709",
            "horseId": "2018102454",
            "umaban": "12"
        },
        {
            "raceId": "202307010709",
            "horseId": "2018105556",
            "umaban": "13"
        },
        {
            "raceId": "202307010709",
            "horseId": "2018102584",
            "umaban": "14"
        },
        {
            "raceId": "202307010709",
            "horseId": "2017105055",
            "umaban": "15"
        },
        {
            "raceId": "202307010708",
            "horseId": "2019102155",
            "umaban": "10"
        },
        {
            "raceId": "202307010707",
            "horseId": "2017104682",
            "umaban": "4"
        },
        {
            "raceId": "202307010707",
            "horseId": "2017100450",
            "umaban": "13"
        }
    ]
}