{
    "horses": [
        {
            "raceId": "201906030802",
            "horseId": "2016102931",
            "umaban": "2"
        },
        {
            "raceId": "201906030802",
            "horseId": "2016100860",
            "umaban": "3"
        },
        {
            "raceId": "201906030802",
            "horseId": "2016100154",
            "umaban": "7"
        },
        {
            "raceId": "201906030802",
            "horseId": "2016104037",
            "umaban": "8"
        },
        {
            "raceId": "201906030802",
            "horseId": "2016102346",
            "umaban": "9"
        },
        {
            "raceId": "201906030802",
            "horseId": "2016101584",
            "umaban": "10"
        },
        {
            "raceId": "201906030802",
            "horseId": "2016100404",
            "umaban": "12"
        },
        {
            "raceId": "201906030802",
            "horseId": "2016100077",
            "umaban": "14"
        },
        {
            "raceId": "201906030802",
            "horseId": "2016105554",
            "umaban": "16"
        },
        {
            "raceId": "201906030801",
            "horseId": "2016102429",
            "umaban": "1"
        },
        {
            "raceId": "201906030801",
            "horseId": "2016100602",
            "umaban": "4"
        },
        {
            "raceId": "201906030801",
            "horseId": "2016103580",
            "umaban": "6"
        },
        {
            "raceId": "201906030801",
            "horseId": "2016104664",
            "umaban": "7"
        },
        {
            "raceId": "201906030801",
            "horseId": "2016103514",
            "umaban": "12"
        },
        {
            "raceId": "201906030801",
            "horseId": "2016103922",
            "umaban": "13"
        },
        {
            "raceId": "201906030712",
            "horseId": "2014106155",
            "umaban": "2"
        },
        {
            "raceId": "201906030711",
            "horseId": "2010103225",
            "umaban": "1"
        },
        {
            "raceId": "201906030711",
            "horseId": "2014104766",
            "umaban": "6"
        },
        {
            "raceId": "201906030710",
            "horseId": "2012100601",
            "umaban": "2"
        },
        {
            "raceId": "201906030710",
            "horseId": "2015100355",
            "umaban": "9"
        },
        {
            "raceId": "201906030709",
            "horseId": "2016106278",
            "umaban": "3"
        },
        {
            "raceId": "201906030708",
            "horseId": "2015104562",
            "umaban": "3"
        },
        {
            "raceId": "201906030708",
            "horseId": "2015109079",
            "umaban": "4"
        },
        {
            "raceId": "201906030708",
            "horseId": "2015105243",
            "umaban": "9"
        },
        {
            "raceId": "201906030707",
            "horseId": "2014104975",
            "umaban": "10"
        },
        {
            "raceId": "201906030706",
            "horseId": "2016109072",
            "umaban": "1"
        },
        {
            "raceId": "201906030706",
            "horseId": "2016103733",
            "umaban": "3"
        },
        {
            "raceId": "201906030706",
            "horseId": "2016100753",
            "umaban": "7"
        },
        {
            "raceId": "201906030706",
            "horseId": "2016102847",
            "umaban": "8"
        },
        {
            "raceId": "201906030705",
            "horseId": "2016104259",
            "umaban": "1"
        },
        {
            "raceId": "201906030705",
            "horseId": "2016110136",
            "umaban": "2"
        },
        {
            "raceId": "201906030705",
            "horseId": "2016105897",
            "umaban": "3"
        },
        {
            "raceId": "201906030705",
            "horseId": "2016105254",
            "umaban": "4"
        },
        {
            "raceId": "201906030705",
            "horseId": "2016104385",
            "umaban": "5"
        },
        {
            "raceId": "201906030705",
            "horseId": "2016105040",
            "umaban": "6"
        },
        {
            "raceId": "201906030705",
            "horseId": "2016101210",
            "umaban": "8"
        },
        {
            "raceId": "201906030705",
            "horseId": "2016100406",
            "umaban": "10"
        },
        {
            "raceId": "201906030705",
            "horseId": "2016102576",
            "umaban": "14"
        },
        {
            "raceId": "201906030705",
            "horseId": "2016110047",
            "umaban": "17"
        },
        {
            "raceId": "201906030704",
            "horseId": "2016103093",
            "umaban": "1"
        },
        {
            "raceId": "201906030704",
            "horseId": "2016105920",
            "umaban": "3"
        },
        {
            "raceId": "201906030704",
            "horseId": "2016103368",
            "umaban": "4"
        },
        {
            "raceId": "201906030704",
            "horseId": "2016101290",
            "umaban": "10"
        },
        {
            "raceId": "201906030704",
            "horseId": "2016100787",
            "umaban": "11"
        },
        {
            "raceId": "201906030703",
            "horseId": "2016100280",
            "umaban": "1"
        },
        {
            "raceId": "201906030703",
            "horseId": "2016101334",
            "umaban": "4"
        },
        {
            "raceId": "201906030703",
            "horseId": "2016106340",
            "umaban": "5"
        },
        {
            "raceId": "201906030703",
            "horseId": "2016100813",
            "umaban": "7"
        },
        {
            "raceId": "201906030703",
            "horseId": "2016103379",
            "umaban": "9"
        },
        {
            "raceId": "201906030703",
            "horseId": "2016104996",
            "umaban": "14"
        },
        {
            "raceId": "201906030703",
            "horseId": "2016102703",
            "umaban": "15"
        },
        {
            "raceId": "201906030702",
            "horseId": "2016103401",
            "umaban": "1"
        },
        {
            "raceId": "201906030702",
            "horseId": "2016102841",
            "umaban": "3"
        },
        {
            "raceId": "201906030702",
            "horseId": "2016105059",
            "umaban": "4"
        },
        {
            "raceId": "201906030702",
            "horseId": "2016101691",
            "umaban": "5"
        },
        {
            "raceId": "201906030702",
            "horseId": "2016102807",
            "umaban": "6"
        },
        {
            "raceId": "201906030702",
            "horseId": "2016102180",
            "umaban": "8"
        },
        {
            "raceId": "201906030701",
            "horseId": "2016104597",
            "umaban": "2"
        },
        {
            "raceId": "201906030701",
            "horseId": "2016105803",
            "umaban": "3"
        },
        {
            "raceId": "201906030701",
            "horseId": "2016102681",
            "umaban": "4"
        },
        {
            "raceId": "201906030701",
            "horseId": "2016105224",
            "umaban": "5"
        },
        {
            "raceId": "201906030701",
            "horseId": "2016104151",
            "umaban": "7"
        },
        {
            "raceId": "201906030701",
            "horseId": "2016100544",
            "umaban": "9"
        },
        {
            "raceId": "201906030701",
            "horseId": "2016100062",
            "umaban": "10"
        },
        {
            "raceId": "201906030701",
            "horseId": "2016103598",
            "umaban": "11"
        },
        {
            "raceId": "201906030701",
            "horseId": "2016105593",
            "umaban": "12"
        },
        {
            "raceId": "201906030701",
            "horseId": "2016100457",
            "umaban": "14"
        },
        {
            "raceId": "201906030701",
            "horseId": "2016100064",
            "umaban": "15"
        },
        {
            "raceId": "201906030701",
            "horseId": "2016102712",
            "umaban": "16"
        },
        {
            "raceId": "201906030612",
            "horseId": "2013100590",
            "umaban": "5"
        },
        {
            "raceId": "201906030612",
            "horseId": "2011103768",
            "umaban": "10"
        },
        {
            "raceId": "201906030612",
            "horseId": "2012102736",
            "umaban": "13"
        },
        {
            "raceId": "201906030611",
            "horseId": "2011105200",
            "umaban": "9"
        },
        {
            "raceId": "201906030610",
            "horseId": "2013103933",
            "umaban": "6"
        },
        {
            "raceId": "201906030610",
            "horseId": "2014105879",
            "umaban": "10"
        },
        {
            "raceId": "201906030608",
            "horseId": "2014109051",
            "umaban": "1"
        },
        {
            "raceId": "201906030608",
            "horseId": "2015102464",
            "umaban": "4"
        },
        {
            "raceId": "201906030608",
            "horseId": "2013102403",
            "umaban": "6"
        },
        {
            "raceId": "201906030608",
            "horseId": "2015103112",
            "umaban": "8"
        },
        {
            "raceId": "201906030607",
            "horseId": "2015103951",
            "umaban": "1"
        },
        {
            "raceId": "201906030607",
            "horseId": "2012100798",
            "umaban": "4"
        },
        {
            "raceId": "201906030606",
            "horseId": "2016105139",
            "umaban": "11"
        },
        {
            "raceId": "201906030605",
            "horseId": "2016102070",
            "umaban": "3"
        },
        {
            "raceId": "201906030605",
            "horseId": "2016100704",
            "umaban": "4"
        },
        {
            "raceId": "201906030605",
            "horseId": "2016103280",
            "umaban": "6"
        },
        {
            "raceId": "201906030605",
            "horseId": "2016102794",
            "umaban": "7"
        },
        {
            "raceId": "201906030605",
            "horseId": "2016104978",
            "umaban": "9"
        },
        {
            "raceId": "201906030605",
            "horseId": "2016103587",
            "umaban": "10"
        },
        {
            "raceId": "201906030605",
            "horseId": "2016105077",
            "umaban": "11"
        },
        {
            "raceId": "201906030605",
            "horseId": "2016106110",
            "umaban": "12"
        },
        {
            "raceId": "201906030605",
            "horseId": "2016104446",
            "umaban": "15"
        },
        {
            "raceId": "201906030605",
            "horseId": "2016102721",
            "umaban": "16"
        },
        {
            "raceId": "201906030604",
            "horseId": "2016104974",
            "umaban": "1"
        },
        {
            "raceId": "201906030604",
            "horseId": "2016105261",
            "umaban": "5"
        },
        {
            "raceId": "201906030604",
            "horseId": "2016100820",
            "umaban": "6"
        },
        {
            "raceId": "201906030604",
            "horseId": "2016100581",
            "umaban": "8"
        },
        {
            "raceId": "201906030604",
            "horseId": "2016105283",
            "umaban": "10"
        },
        {
            "raceId": "201906030604",
            "horseId": "2016105207",
            "umaban": "13"
        },
        {
            "raceId": "201906030604",
            "horseId": "2016105025",
            "umaban": "14"
        },
        {
            "raceId": "201906030603",
            "horseId": "2016106595",
            "umaban": "3"
        }
    ]
}