{
    "horses": [
        {
            "raceId": "202408060211",
            "horseId": "2020100142",
            "umaban": "7"
        },
        {
            "raceId": "202408060205",
            "horseId": "2022110042",
            "umaban": "9"
        },
        {
            "raceId": "202408060202",
            "horseId": "2022101672",
            "umaban": "5"
        },
        {
            "raceId": "202408060201",
            "horseId": "2022106267",
            "umaban": "7"
        },
        {
            "raceId": "202408060110",
            "horseId": "2019101222",
            "umaban": "13"
        },
        {
            "raceId": "202408060104",
            "horseId": "2022100570",
            "umaban": "5"
        },
        {
            "raceId": "202408060101",
            "horseId": "2022103910",
            "umaban": "6"
        },
        {
            "raceId": "202408050812",
            "horseId": "2019105915",
            "umaban": "7"
        },
        {
            "raceId": "202408050811",
            "horseId": "2018105043",
            "umaban": "6"
        },
        {
            "raceId": "202408050811",
            "horseId": "2016103387",
            "umaban": "9"
        },
        {
            "raceId": "202408050808",
            "horseId": "2019102886",
            "umaban": "2"
        },
        {
            "raceId": "202408050808",
            "horseId": "2021104407",
            "umaban": "5"
        },
        {
            "raceId": "202408050808",
            "horseId": "2020106813",
            "umaban": "13"
        },
        {
            "raceId": "202408050806",
            "horseId": "2020101869",
            "umaban": "10"
        },
        {
            "raceId": "202408050804",
            "horseId": "2022104105",
            "umaban": "12"
        },
        {
            "raceId": "202408050803",
            "horseId": "2022102549",
            "umaban": "6"
        },
        {
            "raceId": "202408050802",
            "horseId": "2022101537",
            "umaban": "2"
        },
        {
            "raceId": "202408050802",
            "horseId": "2022103077",
            "umaban": "4"
        },
        {
            "raceId": "202408050802",
            "horseId": "2022100125",
            "umaban": "10"
        },
        {
            "raceId": "202408050802",
            "horseId": "2022104155",
            "umaban": "13"
        },
        {
            "raceId": "202408050711",
            "horseId": "2019105938",
            "umaban": "3"
        },
        {
            "raceId": "202408050710",
            "horseId": "2020103648",
            "umaban": "9"
        },
        {
            "raceId": "202408050702",
            "horseId": "2022102006",
            "umaban": "9"
        },
        {
            "raceId": "202408050701",
            "horseId": "2022103167",
            "umaban": "11"
        },
        {
            "raceId": "202408050612",
            "horseId": "2020110153",
            "umaban": "3"
        },
        {
            "raceId": "202408050610",
            "horseId": "2019102220",
            "umaban": "4"
        },
        {
            "raceId": "202408050608",
            "horseId": "2022102711",
            "umaban": "8"
        },
        {
            "raceId": "202408050607",
            "horseId": "2019105063",
            "umaban": "12"
        },
        {
            "raceId": "202408050512",
            "horseId": "2020101578",
            "umaban": "2"
        },
        {
            "raceId": "202408050512",
            "horseId": "2019109159",
            "umaban": "5"
        },
        {
            "raceId": "202408050512",
            "horseId": "2018104149",
            "umaban": "11"
        },
        {
            "raceId": "202408050510",
            "horseId": "2020103565",
            "umaban": "7"
        },
        {
            "raceId": "202408050508",
            "horseId": "2021103859",
            "umaban": "5"
        },
        {
            "raceId": "202408050504",
            "horseId": "2022104510",
            "umaban": "2"
        },
        {
            "raceId": "202408050501",
            "horseId": "2022107247",
            "umaban": "10"
        },
        {
            "raceId": "202408050411",
            "horseId": "2021105764",
            "umaban": "9"
        },
        {
            "raceId": "202408050405",
            "horseId": "2022102647",
            "umaban": "2"
        },
        {
            "raceId": "202408050403",
            "horseId": "2022106788",
            "umaban": "5"
        },
        {
            "raceId": "202408050312",
            "horseId": "2020106795",
            "umaban": "3"
        },
        {
            "raceId": "202408050312",
            "horseId": "2018104322",
            "umaban": "11"
        },
        {
            "raceId": "202408050311",
            "horseId": "2017103688",
            "umaban": "5"
        },
        {
            "raceId": "202408050311",
            "horseId": "2020103070",
            "umaban": "7"
        },
        {
            "raceId": "202408050311",
            "horseId": "2018102657",
            "umaban": "9"
        },
        {
            "raceId": "202408050309",
            "horseId": "2019103346",
            "umaban": "2"
        },
        {
            "raceId": "202408050305",
            "horseId": "2022104206",
            "umaban": "5"
        },
        {
            "raceId": "202408050303",
            "horseId": "2022105265",
            "umaban": "10"
        },
        {
            "raceId": "202408050302",
            "horseId": "2022101123",
            "umaban": "5"
        },
        {
            "raceId": "202408050301",
            "horseId": "2022102561",
            "umaban": "6"
        },
        {
            "raceId": "202408050301",
            "horseId": "2022105539",
            "umaban": "14"
        },
        {
            "raceId": "202408050111",
            "horseId": "2018102595",
            "umaban": "3"
        },
        {
            "raceId": "202408050111",
            "horseId": "2017105097",
            "umaban": "4"
        },
        {
            "raceId": "202408050111",
            "horseId": "2016110119",
            "umaban": "17"
        },
        {
            "raceId": "202408050110",
            "horseId": "2019103428",
            "umaban": "5"
        },
        {
            "raceId": "202408050101",
            "horseId": "2022106491",
            "umaban": "9"
        },
        {
            "raceId": "202408040811",
            "horseId": "2019105283",
            "umaban": "4"
        },
        {
            "raceId": "202408040810",
            "horseId": "2018101514",
            "umaban": "2"
        },
        {
            "raceId": "202408040810",
            "horseId": "2019105709",
            "umaban": "6"
        },
        {
            "raceId": "202408040810",
            "horseId": "2019103791",
            "umaban": "15"
        },
        {
            "raceId": "202408040809",
            "horseId": "2021109157",
            "umaban": "9"
        },
        {
            "raceId": "202408040807",
            "horseId": "2020100508",
            "umaban": "1"
        },
        {
            "raceId": "202408040806",
            "horseId": "2021106207",
            "umaban": "1"
        },
        {
            "raceId": "202408040806",
            "horseId": "2021100885",
            "umaban": "4"
        },
        {
            "raceId": "202408040806",
            "horseId": "2021102517",
            "umaban": "6"
        },
        {
            "raceId": "202408040806",
            "horseId": "2021104071",
            "umaban": "7"
        },
        {
            "raceId": "202408040806",
            "horseId": "2021101894",
            "umaban": "10"
        },
        {
            "raceId": "202408040804",
            "horseId": "2021101469",
            "umaban": "5"
        },
        {
            "raceId": "202408040804",
            "horseId": "2021106512",
            "umaban": "6"
        },
        {
            "raceId": "202408040804",
            "horseId": "2021102216",
            "umaban": "10"
        },
        {
            "raceId": "202408040804",
            "horseId": "2021101633",
            "umaban": "18"
        },
        {
            "raceId": "202408040803",
            "horseId": "2021103142",
            "umaban": "2"
        },
        {
            "raceId": "202408040802",
            "horseId": "2021102260",
            "umaban": "3"
        },
        {
            "raceId": "202408040802",
            "horseId": "2021101585",
            "umaban": "10"
        },
        {
            "raceId": "202408040801",
            "horseId": "2021100167",
            "umaban": "3"
        },
        {
            "raceId": "202408040801",
            "horseId": "2021107332",
            "umaban": "6"
        },
        {
            "raceId": "202408040801",
            "horseId": "2021102509",
            "umaban": "8"
        },
        {
            "raceId": "202408040801",
            "horseId": "2021100274",
            "umaban": "12"
        },
        {
            "raceId": "202408040801",
            "horseId": "2021103594",
            "umaban": "16"
        },
        {
            "raceId": "202408040711",
            "horseId": "2019103826",
            "umaban": "1"
        },
        {
            "raceId": "202408040711",
            "horseId": "2017110120",
            "umaban": "12"
        },
        {
            "raceId": "202408040710",
            "horseId": "2018100141",
            "umaban": "1"
        },
        {
            "raceId": "202408040710",
            "horseId": "2020101632",
            "umaban": "12"
        },
        {
            "raceId": "202408040710",
            "horseId": "2019105545",
            "umaban": "16"
        },
        {
            "raceId": "202408040708",
            "horseId": "2020103095",
            "umaban": "15"
        },
        {
            "raceId": "202408040706",
            "horseId": "2021103164",
            "umaban": "1"
        },
        {
            "raceId": "202408040706",
            "horseId": "2021106162",
            "umaban": "6"
        },
        {
            "raceId": "202408040706",
            "horseId": "2021106536",
            "umaban": "7"
        },
        {
            "raceId": "202408040706",
            "horseId": "2021106160",
            "umaban": "9"
        },
        {
            "raceId": "202408040705",
            "horseId": "2022105476",
            "umaban": "6"
        },
        {
            "raceId": "202408040704",
            "horseId": "2021105446",
            "umaban": "3"
        },
        {
            "raceId": "202408040704",
            "horseId": "2021105277",
            "umaban": "8"
        },
        {
            "raceId": "202408040704",
            "horseId": "2021106566",
            "umaban": "9"
        },
        {
            "raceId": "202408040704",
            "horseId": "2021104743",
            "umaban": "12"
        },
        {
            "raceId": "202408040704",
            "horseId": "2021100990",
            "umaban": "13"
        },
        {
            "raceId": "202408040703",
            "horseId": "2021104190",
            "umaban": "13"
        },
        {
            "raceId": "202408040703",
            "horseId": "2021103056",
            "umaban": "14"
        },
        {
            "raceId": "202408040703",
            "horseId": "2021104500",
            "umaban": "15"
        },
        {
            "raceId": "202408040702",
            "horseId": "2021103779",
            "umaban": "1"
        },
        {
            "raceId": "202408040702",
            "horseId": "2021105001",
            "umaban": "7"
        },
        {
            "raceId": "202408040702",
            "horseId": "2021106183",
            "umaban": "16"
        },
        {
            "raceId": "202408040612",
            "horseId": "2020101200",
            "umaban": "6"
        }
    ]
}